tccli/__init__.py
tccli/argparser.py
tccli/argument.py
tccli/base_command.py
tccli/cli_input_json.py
tccli/cli_unfold_argument.py
tccli/command.py
tccli/completer.py
tccli/configure.py
tccli/credentials.py
tccli/document_handler.py
tccli/error_msg.py
tccli/exceptions.py
tccli/format_output.py
tccli/generatecliskeleton.py
tccli/help_command.py
tccli/loaders.py
tccli/log.py
tccli/main.py
tccli/oauth.py
tccli/options_define.py
tccli/plugin.py
tccli/sso.py
tccli/style.py
tccli/table.py
tccli/text.py
tccli/utils.py
tccli/advance/__init__.py
tccli/advance/userConfigHandler.py
tccli/advance/userProfileHandler.py
tccli/colorama/__init__.py
tccli/colorama/ansi.py
tccli/colorama/ansitowin32.py
tccli/colorama/initialise.py
tccli/colorama/win32.py
tccli/colorama/winterm.py
tccli/plugins/__init__.py
tccli/plugins/auth/__init__.py
tccli/plugins/auth/browser_flow.py
tccli/plugins/auth/login.py
tccli/plugins/auth/logout.py
tccli/plugins/auth/texts.py
tccli/plugins/sso/__init__.py
tccli/plugins/sso/configs.py
tccli/plugins/sso/configure.py
tccli/plugins/sso/login.py
tccli/plugins/sso/logout.py
tccli/plugins/sso/terminal.py
tccli/plugins/sso/texts.py
tccli/plugins/test/__init__.py
tccli/plugins/test/add.py
tccli/services/MANIFEST.in
tccli/services/__init__.py
tccli/services/aai/__init__.py
tccli/services/aai/aai_client.py
tccli/services/aai/v20180522/api.json
tccli/services/aai/v20180522/examples.json
tccli/services/aca/__init__.py
tccli/services/aca/aca_client.py
tccli/services/aca/v20210323/api.json
tccli/services/aca/v20210323/examples.json
tccli/services/acp/__init__.py
tccli/services/acp/acp_client.py
tccli/services/acp/v20220105/api.json
tccli/services/acp/v20220105/examples.json
tccli/services/advisor/__init__.py
tccli/services/advisor/advisor_client.py
tccli/services/advisor/v20200721/api.json
tccli/services/advisor/v20200721/examples.json
tccli/services/af/__init__.py
tccli/services/af/af_client.py
tccli/services/af/v20200226/api.json
tccli-3.1.41.1.dist-info/METADATA
tccli-3.1.41.1.dist-info/WHEEL
tccli-3.1.41.1.dist-info/entry_points.txt
tccli-3.1.41.1.dist-info/licenses/LICENSE
tccli-3.1.41.1.dist-info/RECORD
