Metadata-Version: 2.4
Name: tccli
Version: 3.1.41.1
Summary: Universal Command Line Environment for Tencent Cloud
Project-URL: Homepage, https://github.com/TencentCloud/tencentcloud-cli
Project-URL: Bug Tracker, https://github.com/TencentCloud/tencentcloud-cli/issues
Author-email: tencentcloudapi <tencentcloudapi@tencent.com>
License-File: LICENSE
Classifier: Development Status :: 5 - Production/Stable
Classifier: Intended Audience :: Developers
Classifier: License :: OSI Approved :: Apache Software License
Classifier: Operating System :: OS Independent
Classifier: Programming Language :: Python :: 2.7
Classifier: Programming Language :: Python :: 3
Requires-Dist: jmespath==0.10.0
Requires-Dist: six==1.16.0
Requires-Dist: tencentcloud-sdk-python>=3.1.41
